__init__.py
firewall_handler.py
main.py
path_handler.py
Photo_Composition_Designer/__init__.py
Photo_Composition_Designer/__main__.py
Photo_Composition_Designer/_version.py
Photo_Composition_Designer/cli/__init__.py
Photo_Composition_Designer/cli/__main__.py
Photo_Composition_Designer/cli/cli.py
Photo_Composition_Designer/common/Anniversaries.py
Photo_Composition_Designer/common/Locations.py
Photo_Composition_Designer/common/MoonPhase.py
Photo_Composition_Designer/common/Photo.py
Photo_Composition_Designer/common/__init__.py
Photo_Composition_Designer/config/__init__.py
Photo_Composition_Designer/config/config.py
Photo_Composition_Designer/core/__init__.py
Photo_Composition_Designer/core/base.py
Photo_Composition_Designer/gui/GuiLogWriter.py
Photo_Composition_Designer/gui/__init__.py
Photo_Composition_Designer/gui/__main__.py
Photo_Composition_Designer/gui/gui.py
Photo_Composition_Designer/image/CalendarRenderer.py
Photo_Composition_Designer/image/CollageRenderer.py
Photo_Composition_Designer/image/DescriptionRenderer.py
Photo_Composition_Designer/image/MapRenderer.py
Photo_Composition_Designer/image/__init__.py
Photo_Composition_Designer/tools/DescriptionsFileGenerator.py
Photo_Composition_Designer/tools/GeoPlotter.py
Photo_Composition_Designer/tools/Helpers.py
Photo_Composition_Designer/tools/ImageDistributor.py
Photo_Composition_Designer/tools/__init__.py
photo_composition_designer-1.0.0.dist-info/licenses/LICENSE
photo_composition_designer-1.0.0.dist-info/METADATA
photo_composition_designer-1.0.0.dist-info/WHEEL
photo_composition_designer-1.0.0.dist-info/entry_points.txt
photo_composition_designer-1.0.0.dist-info/top_level.txt
photo_composition_designer-1.0.0.dist-info/RECORD
